common_primitives/__init__.py
common_primitives/add_semantic_types.py
common_primitives/audio_reader.py
common_primitives/base.py
common_primitives/cast_to_type.py
common_primitives/column_map.py
common_primitives/column_parser.py
common_primitives/compute_metafeatures.py
common_primitives/compute_unique_values.py
common_primitives/construct_confidence.py
common_primitives/construct_predictions.py
common_primitives/csv_reader.py
common_primitives/cut_audio.py
common_primitives/dataframe_flatten.py
common_primitives/dataframe_image_reader.py
common_primitives/dataframe_list_extractor.py
common_primitives/dataframe_sampling.py
common_primitives/dataframe_to_list.py
common_primitives/dataframe_to_ndarray.py
common_primitives/dataframe_utils.py
common_primitives/datamart_augment.py
common_primitives/dataset_map.py
common_primitives/dataset_sample.py
common_primitives/dataset_to_dataframe.py
common_primitives/dataset_utils.py
common_primitives/datetime_field_compose.py
common_primitives/datetime_range_filter.py
common_primitives/denormalize.py
common_primitives/extract_columns.py
common_primitives/extract_columns_semantic_types.py
common_primitives/extract_columns_structural_types.py
common_primitives/fixed_split.py
common_primitives/grouping_field_compose.py
common_primitives/horizontal_concat.py
common_primitives/kfold_split.py
common_primitives/kfold_split_timeseries.py
common_primitives/lgbm_classifier.py
common_primitives/list_to_dataframe.py
common_primitives/list_to_ndarray.py
common_primitives/multi_horizontal_concat.py
common_primitives/ndarray_to_dataframe.py
common_primitives/ndarray_to_list.py
common_primitives/no_split.py
common_primitives/normalize_column_references.py
common_primitives/numeric_range_filter.py
common_primitives/one_hot_maker.py
common_primitives/pandas_onehot_encoder.py
common_primitives/random_forest.py
common_primitives/ravel.py
common_primitives/redact_columns.py
common_primitives/regex_filter.py
common_primitives/remove_columns.py
d3m_common_primitives-2022.5.26.dist-info/LICENSE.txt
d3m_common_primitives-2022.5.26.dist-info/METADATA
d3m_common_primitives-2022.5.26.dist-info/WHEEL
d3m_common_primitives-2022.5.26.dist-info/entry_points.txt
d3m_common_primitives-2022.5.26.dist-info/top_level.txt
d3m_common_primitives-2022.5.26.dist-info/RECORD
