Metadata-Version: 2.1
Name: d3m-common-primitives
Version: 2022.5.26
Summary: D3M common primitives
Home-page: https://gitlab.com/datadrivendiscovery/common-primitives
Author: common-primitives
License: Apache-2.0
Platform: UNKNOWN
Classifier: License :: OSI Approved :: Apache Software License
Requires-Dist: d3m (==2022.5.5)
Requires-Dist: datamart-rest (==0.2.7)
Requires-Dist: datamart (==2021.3.17)
Requires-Dist: imageio (<3.0,>=2.3.0)
Requires-Dist: lightgbm (<2.4.0,>=2.2.2)
Requires-Dist: numpy
Requires-Dist: pandas
Requires-Dist: pillow (==7.1.2)
Requires-Dist: pyprctl (<0.2,>=0.1)
Requires-Dist: scikit-learn
Requires-Dist: shap (<0.41.0,>=0.37.0)
Requires-Dist: xgboost (<0.91,>=0.81)
Provides-Extra: opencv
Requires-Dist: opencv-python (<4.5.58,>=4.1) ; extra == 'opencv'
Provides-Extra: opencv-headless
Requires-Dist: opencv-python-headless (<=4.5.4.58,>=4.1) ; extra == 'opencv-headless'
